Workbook
Name anos: Planilha1!$D$24
Name dividendo_mensais: Planilha1!$D$27
Name investimento_mes: Planilha1!$D$23
Name patrimonio: Planilha1!$D$26
Name rendimento: Planilha1!$D$18
Name rendimento_carteira: Planilha1!$D$13
Name salario: Planilha1!$D$17
Name taxa_rendimento: Planilha1!$D$25
Name taxa_rendimento_mensal: Planilha1!$D$25

Sheet Planilha1
B15: CONFIGURAÇÕES
B17: Salário | D17: 2000
B18: Rendimento Carteira | D18: 0.006
B19: Sugestão de Investimento (30%) | D19: =D17*30% -> 600
B21: INVESTIMENTO MENSAL
B23: Quanto investir por mês ? | D23: 200
B24: Por Quantos Anos ? | D24: 5
B25: Taxa de Rendimento mensal ? | D25: 0.01079
B26: Patrimônio acumulado ? | D26: =FV(D25,D24*12,D23*-1) -> 16755.383
B27: Dividendos Mensais ? | D27: =D26*$D$18 -> 100.5323
B29: CENÁRIOS | E29: DIVIDENDO
A31: 2 | B31: Quanto em 2 Anos ? | D31: =FV($D$25,$A31*12,$D$23*-1) -> 5445.5255 | E31: =D31*$D$18 -> 32.673153
A32: 5 | B32: Quanto em 5 Anos ? | D32: =FV($D$25,$A32*12,$D$23*-1) -> 16755.383 | E32: =D32*$D$18 -> 100.5323
A33: 10 | B33: Quanto em 10 Anos ? | D33: =FV($D$25,$A33*12,$D$23*-1) -> 48656.843 | E33: =D33*$D$18 -> 291.94106
A34: 20 | B34: Quanto em 20 Anos ? | D34: =FV($D$25,$A34*12,$D$23*-1) -> 225039.68 | E34: =D34*$D$18 -> 1350.2381
A35: 30 | B35: Quanto em 30 Anos ? | D35: =FV($D$25,$A35*12,$D$23*-1) -> 864433.93 | E35: =D35*$D$18 -> 5186.6036
B40: Perfil | D40: AGRESSIVO
B41: VALOR A SER INVESTIDO POR MÊS | D41: =investimento_mes -> 200
B43: TIPO DE FII | D43: PORCENTUAL SUGERIDO | E43: VALORES
B44: PAPEL | D44: =VLOOKUP(_xlfn.CONCAT($D$40,"-",B44),Planilha2!$A$3:$D$21,4,FALSE) -> 0.5 | E44: =D44*$D$41 -> 100
B45: TIJOLO | D45: =VLOOKUP(_xlfn.CONCAT($D$40,"-",B45),Planilha2!$A$3:$D$21,4,FALSE) -> 0.1 | E45: =D45*$D$41 -> 20
B46: HÍBRIDOS | D46: =VLOOKUP(_xlfn.CONCAT($D$40,"-",B46),Planilha2!$A$3:$D$21,4,FALSE) -> 0.05 | E46: =D46*$D$41 -> 10
B47: FOFs | D47: =VLOOKUP(_xlfn.CONCAT($D$40,"-",B47),Planilha2!$A$3:$D$21,4,FALSE) -> 0.05 | E47: =D47*$D$41 -> 10
B48: DESENVOLVIMENTO | D48: =VLOOKUP(_xlfn.CONCAT($D$40,"-",B48),Planilha2!$A$3:$D$21,4,FALSE) -> 0.2 | E48: =D48*$D$41 -> 40
B49: HOTELARIAS | D49: =VLOOKUP(_xlfn.CONCAT($D$40,"-",B49),Planilha2!$A$3:$D$21,4,FALSE) -> 0.1 | E49: =D49*$D$41 -> 20
E50: =SUM(E44:E49) -> 200

Sheet Planilha2
A3: CHAVE | B3: PERFIL | C3: TIPO DE FII | D3: % | G3: %
A4: =_xlfn.CONCAT($B$4,"-",C4) -> CONSERVADOR-PAPEL | B4: CONSERVADOR | C4: PAPEL | D4: 0.3 | F4: CONSERVADOR - PAPEL | G4: =VLOOKUP($F$4,$A$3:$D$21,4,FALSE) -> #N/A
A5: =_xlfn.CONCAT($B$4,"-",C5) -> CONSERVADOR-TIJOLO | B5: CONSERVADOR | C5: TIJOLO | D5: 0.5
A6: =_xlfn.CONCAT($B$4,"-",C6) -> CONSERVADOR-HÍBRIDOS | B6: CONSERVADOR | C6: HÍBRIDOS | D6: 0.1
A7: =_xlfn.CONCAT($B$4,"-",C7) -> CONSERVADOR-FOFs | B7: CONSERVADOR | C7: FOFs | D7: 0.1
A8: =_xlfn.CONCAT($B$4,"-",C8) -> CONSERVADOR-DESENVOLVIMENTO | B8: CONSERVADOR | C8: DESENVOLVIMENTO | D8: 0
A9: =_xlfn.CONCAT($B$4,"-",C9) -> CONSERVADOR-HOTELARIAS | B9: CONSERVADOR | C9: HOTELARIAS | D9: 0
A10: =_xlfn.CONCAT($B$10,"-",C10) -> MODERADO-PAPEL | B10: MODERADO | C10: PAPEL | D10: 0.32
A11: =_xlfn.CONCAT($B$10,"-",C11) -> MODERADO-TIJOLO | B11: MODERADO | C11: TIJOLO | D11: 0.35
A12: =_xlfn.CONCAT($B$10,"-",C12) -> MODERADO-HÍBRIDOS | B12: MODERADO | C12: HÍBRIDOS | D12: 0.08
A13: =_xlfn.CONCAT($B$10,"-",C13) -> MODERADO-FOFs | B13: MODERADO | C13: FOFs | D13: 0.05
A14: =_xlfn.CONCAT($B$10,"-",C14) -> MODERADO-DESENVOLVIMENTO | B14: MODERADO | C14: DESENVOLVIMENTO | D14: 0.1
A15: =_xlfn.CONCAT($B$10,"-",C15) -> MODERADO-HOTELARIAS | B15: MODERADO | C15: HOTELARIAS | D15: 0.1
A16: =_xlfn.CONCAT($B$16,"-",C16) -> AGRESSIVO-PAPEL | B16: AGRESSIVO | C16: PAPEL | D16: 0.5
A17: =_xlfn.CONCAT($B$16,"-",C17) -> AGRESSIVO-TIJOLO | B17: AGRESSIVO | C17: TIJOLO | D17: 0.1
A18: =_xlfn.CONCAT($B$16,"-",C18) -> AGRESSIVO-HÍBRIDOS | B18: AGRESSIVO | C18: HÍBRIDOS | D18: 0.05
A19: =_xlfn.CONCAT($B$16,"-",C19) -> AGRESSIVO-FOFs | B19: AGRESSIVO | C19: FOFs | D19: 0.05
A20: =_xlfn.CONCAT($B$16,"-",C20) -> AGRESSIVO-DESENVOLVIMENTO | B20: AGRESSIVO | C20: DESENVOLVIMENTO | D20: 0.2
A21: =_xlfn.CONCAT($B$16,"-",C21) -> AGRESSIVO-HOTELARIAS | B21: AGRESSIVO | C21: HOTELARIAS | D21: 0.1
